<xml xmlns:o="urn:schemas-microsoft-com:office:office">
 <o:MainFile HRef="../masinfo.htm"/>
 <o:File HRef="image312.png"/>
 <o:File HRef="image315.png"/>
 <o:File HRef="image316.png"/>
 <o:File HRef="image317.png"/>
 <o:File HRef="image318.png"/>
 <o:File HRef="image319.png"/>
 <o:File HRef="image320.png"/>
 <o:File HRef="image321.png"/>
 <o:File HRef="image322.png"/>
 <o:File HRef="image323.png"/>
 <o:File HRef="image324.png"/>
 <o:File HRef="image325.png"/>
 <o:File HRef="image326.png"/>
 <o:File HRef="image327.png"/>
 <o:File HRef="image328.png"/>
 <o:File HRef="image329.png"/>
 <o:File HRef="image330.png"/>
 <o:File HRef="image331.png"/>
 <o:File HRef="image332.png"/>
 <o:File HRef="image333.png"/>
 <o:File HRef="image334.png"/>
 <o:File HRef="image335.png"/>
 <o:File HRef="image336.png"/>
 <o:File HRef="image337.png"/>
 <o:File HRef="image338.png"/>
 <o:File HRef="image339.png"/>
 <o:File HRef="image340.png"/>
 <o:File HRef="image341.png"/>
 <o:File HRef="image401.png"/>
 <o:File HRef="image405.png"/>
 <o:File HRef="image426.png"/>
 <o:File HRef="image481.png"/>
 <o:File HRef="image482.png"/>
 <o:File HRef="image483.png"/>
 <o:File HRef="image484.png"/>
 <o:File HRef="image485.png"/>
 <o:File HRef="image486.png"/>
 <o:File HRef="image487.png"/>
 <o:File HRef="image488.png"/>
 <o:File HRef="image489.png"/>
 <o:File HRef="image490.png"/>
 <o:File HRef="image491.png"/>
 <o:File HRef="image492.png"/>
 <o:File HRef="image493.png"/>
 <o:File HRef="image494.png"/>
 <o:File HRef="image495.png"/>
 <o:File HRef="image496.png"/>
 <o:File HRef="image497.png"/>
 <o:File HRef="image498.png"/>
 <o:File HRef="image499.png"/>
 <o:File HRef="image500.png"/>
 <o:File HRef="image501.png"/>
 <o:File HRef="image502.png"/>
 <o:File HRef="image503.png"/>
 <o:File HRef="image504.png"/>
 <o:File HRef="image505.png"/>
 <o:File HRef="image506.png"/>
 <o:File HRef="image507.png"/>
 <o:File HRef="image508.png"/>
 <o:File HRef="image518.png"/>
 <o:File HRef="image521.png"/>
 <o:File HRef="image306.png"/>
 <o:File HRef="image293.png"/>
 <o:File HRef="image352.png"/>
 <o:File HRef="image353.png"/>
 <o:File HRef="image342.png"/>
 <o:File HRef="image3421.png"/>
 <o:File HRef="image286.png"/>
 <o:File HRef="image290.png"/>
 <o:File HRef="image2901.png"/>
 <o:File HRef="filelist.xml"/>
</xml>